bluebird/__init__.py
bluebird/http_helper.py
bluebird/scraper.py
bluebird-0.0.9a0.dist-info/LICENSE
bluebird-0.0.9a0.dist-info/METADATA
bluebird-0.0.9a0.dist-info/WHEEL
bluebird-0.0.9a0.dist-info/top_level.txt
bluebird-0.0.9a0.dist-info/RECORD
